scorer_edge_l2dc-0.0.13.dist-info/WHEEL
scorer_edge_l2dc-0.0.13.dist-info/LICENSE
scorer_edge_l2dc-0.0.13.dist-info/RECORD
scorer_edge_l2dc-0.0.13.dist-info/METADATA
scorer_edge_l2dc-0.0.13.dist-info/top_level.txt
scorer_edge/l2dc/__init__.py
scorer_edge/l2dc/__main__.py
scorer_edge/l2dc/_core.cpython-310-x86_64-linux-gnu.so
scorer_edge/l2dc/lib/libl2dc.so
scorer_edge/l2dc/include/scorer_edge/l2dc.hpp
scorer_edge/l2dc/share/cmake/ScorerEdgeL2dcTargets-release.cmake
scorer_edge/l2dc/share/cmake/ScorerEdgeL2dcConfigVersion.cmake
scorer_edge/l2dc/share/cmake/ScorerEdgeL2dcConfig.cmake
scorer_edge/l2dc/share/cmake/ScorerEdgeL2dcTargets.cmake
