Metadata-Version: 2.1
Name: scorer-edge-l2dc
Version: 0.0.13
Summary: A set of schema definitions and API for SCORER Edge L2DC
Home-page: https://github.com/scorer-edge/l2dc
Author: Hideaki Suzuki
Author-email: h2suzuki@gmail.com
Project-URL: Bug Tracker, https://github.com/scorer-edge/l2dc/issues
Classifier: Programming Language :: Python :: 3
Classifier: Programming Language :: C++
Classifier: License :: OSI Approved :: Apache Software License
Classifier: Operating System :: POSIX :: Linux
Classifier: Development Status :: 1 - Planning
Requires-Python: >=3.7
License-File: LICENSE
Requires-Dist: flatbuffers
Requires-Dist: numpy
Requires-Dist: pyzmq
Provides-Extra: test
Requires-Dist: pytest ; extra == 'test'
